api/__init__.py
api/main.py
api/version.py
api/controllers/__init__.py
api/controllers/nodes/__init__.py
devserv/__init__.py
devserv/mock_responses.py
yukon_backend-0.1.2.dist-info/LICENSE.rst
yukon_backend-0.1.2.dist-info/METADATA
yukon_backend-0.1.2.dist-info/WHEEL
yukon_backend-0.1.2.dist-info/entry_points.txt
yukon_backend-0.1.2.dist-info/top_level.txt
yukon_backend-0.1.2.dist-info/RECORD
